README.md
setup.py
Mathstein/__init__.py
Mathstein/matharea.py
Mathstein/matheqn.py
Mathstein/mathmatcalc.py
Mathstein/mathroot.py
Mathstein.egg-info/PKG-INFO
Mathstein.egg-info/SOURCES.txt
Mathstein.egg-info/dependency_links.txt
Mathstein.egg-info/requires.txt
Mathstein.egg-info/top_level.txt
test_cases/__init__.py
test_cases/context.py
test_cases/test_matharea.py
test_cases/test_matheqn.py
test_cases/test_mathmatcalc.py.py
test_cases/test_mathroot.py