Metadata-Version: 1.1
Name: Mathstein
Version: 0.0.1
Summary: It is a comprehensive mathematical library
Home-page: UNKNOWN
Author: Teinstein Education
Author-email: UNKNOWN
License: MIT
Keywords: mathstein
Platform: UNKNOWN
Classifier: Development Status :: 5 - Production/Stable
Classifier: Intended Audience :: Education
Classifier: Operating System :: Microsoft :: Windows :: Windows 10
Classifier: License :: OSI Approved :: MIT License
Classifier: Programming Language :: Python :: 3
